bruck/__init__.py
bruck/__main__.py
bruck/interpreter.py
bruck-0.1.0.dist-info/LICENSE
bruck-0.1.0.dist-info/METADATA
bruck-0.1.0.dist-info/WHEEL
bruck-0.1.0.dist-info/entry_points.txt
bruck-0.1.0.dist-info/top_level.txt
bruck-0.1.0.dist-info/RECORD
