Metadata-Version: 2.1
Name: bruck
Version: 0.1.0
Summary: Write brainfuck with ONLY square brackets.
Home-page: https://github.com/GLanguage/bruck
Author: Alan Han
Author-email: hanyx2006@qq.com
License: MIT License
Keywords: bruck,esolang,esoteric,brainfuck
Platform: UNKNOWN
Classifier: Programming Language :: Python :: 3
Classifier: License :: OSI Approved :: MIT License
Requires-Python: >=3.6
License-File: LICENSE
Requires-Dist: click
